CHANGELOG.txt
LICENSE.txt
MANIFEST.in
README.txt
setup.py
BetterTools/__init__.py
BetterTools.egg-info/PKG-INFO
BetterTools.egg-info/SOURCES.txt
BetterTools.egg-info/dependency_links.txt
BetterTools.egg-info/top_level.txt