Metadata-Version: 1.1
Name: BetterTools
Version: 0.1.1
Summary: This is a lib to improove native fonction, and some usefull one for everyone.
Home-page: https://github.com/Remi-Avec-Un-I/BetterTools
Author: Remi_Avec_Un_I
Author-email: UNKNOWN
License: MIT
Keywords: input,BetterTools,Tools,Better
Platform: UNKNOWN
Classifier: Development Status :: 5 - Production/Stable
Classifier: Intended Audience :: Developers
Classifier: Operating System :: Microsoft :: Windows :: Windows 10
Classifier: License :: OSI Approved :: MIT License
Classifier: Programming Language :: Python :: 3
